apple_peeler/__init__.py
apple_peeler/extract.py
apple_peeler-0.1.1.dist-info/entry_points.txt
apple_peeler-0.1.1.dist-info/LICENSE
apple_peeler-0.1.1.dist-info/WHEEL
apple_peeler-0.1.1.dist-info/METADATA
apple_peeler-0.1.1.dist-info/RECORD
